{
  "url": "http://www.besiweb.com/HKANTAR2.html",
  "file_number": "276",
  "content_hash": "165515dcfb99678b75df71b826c4639b92d9d7ecea43673c319da0e5b61123a0",
  "total_blocks": 96,
  "retained_blocks": 1,
  "ignored_blocks": 95,
  "blocks": [
    {
      "tag": "p",
      "text": "Business &\r\nEconomics Society International 64 Holden Street Worcester, MA 01605-3109, USA Tel: (508) 595-0089, Email: hkan@besiweb.com URL: http://www.besiweb.com B USINESS & E CONOMICS S OCIETY I NTERNATIONAL 2007 C ONFERENCE F RENCH R IVIERA - A NTIBES, F RANCE July 16-20, 2007 Hotel Ambassadeur if !supportLineBreakNewLine endif CALL FOR PARTICIPANTS (Deadline for Abstracts and Early\r\nRegistration: March 15, 2007) The Business & Economics Society International ( B&ESI ) invites you to\r\nparticipate in its 2007 Conference to be held in French Riviera – Antibes / France , at the Hotel Ambassadeur , July 16-20.\r\nThe conference welcomes academics (business/economics professors and\r\nadministrators), as well as corporation / government executives and economists. Participants may organize panels (please ask for or browse the Panel Organizer Guidelines ),\r\npresent papers, participate in poster sessions, chair sessions, discuss papers,\r\nparticipate in round-table discussions, or simply observe. The program will\r\nconsist of: small concurrent sessions with: chairperson, presenters, and at least one\r\ndiscussant assigned to comment on each paper; poster sessions; roundtable thematic discussion sessions with moderator; workshops and panels; time allocated for each presenter is 20 minutes. * To ORGANIZE PANELS please ask for \"Panel Organizer Guidelines\". The\r\nfee for each participant in the panel, except the organizer, is $370. The fee\r\nfor the panel organizer is $180. * To participate as a PRESENTER please submit ABSTRACTS and/or PAPERS: ABSTRACT/PAPER SUBMISSION AND REGISTRATION DEADLINE:\r\nMARCH 15, 2007 Please, submit your abstract (of no more than 200 words) via email hkan@besiweb.com by MARCH 15, 2007.\r\nAdditionally, mail two hard copies of your abstract (see address below). All abstracts submitted\r\nwill be evaluated for presentation and publication in the Book of Abstracts which\r\nwill be available at the Conference; You may submit abstracts for no more than 2 papers; Abstracts/papers must not have been published, accepted, or submitted for\r\npublication elsewhere; The categories that best fit your paper must be typed on the top right corner\r\nof the front page (See below table titled \"Subject Category Title and\r\nNumber\"); For co-authorships please include names, affiliations, and addresses of all\r\nauthors and indicate who will serve as presenter; The title of your abstract(s) or paper(s) is(are): ______________________________________________________________________________________\r\n______________________________________________________________________________________ FINAL PAPER SUBMISSION DEADLINE: APRIL 30, 2007 Please submit via post 2 hard copies of the paper(s) and a disk containing\r\nthe manuscript(s) in Word by APRIL 30, 2007. Unless you instruct us otherwise, all papers will pass a blind peer review\r\nprocess for publication consideration in the '2007 GLOBAL BUSINESS &\r\nECONOMICS ANTHOLOGY', a volume of selected papers from the Conference. Format\r\ninstructions will be attached to the acceptance for publication letter.\r\n[Manuscripts of more than 12 single-spaced pages of text (font: times, size=10)\r\ninclusive of graphs, tables, endnotes and references will be considered at $10\r\nper additional page]; Authorship should be identified only on a removable cover page. CONFERENCE\r\nREGISTRATION FORM if !supportEmptyParas endif Last Name\r\n__________________________________________________________________________________________ First Name and M.I.\r\n___________________________________________________________________________________ Nickname for Badge\r\n___________________________________________________________________________________ Position/Title/Rank\r\n____________________________________________________________________________________ Affiliation\r\n___________________________________________________________________________________________ Mailing Address ______________________________________________________________________________________\r\n___________________________________________________________________________________________________ Telephone: Day (___)____________________ , Fax (___)_________________________ E-Mail: ___________________________________ [Iwish to serve as a DISCUSSANT____ and/or a SESSION CHAIR/MODERATOR\r\n____.My specialty is______________________. \"Session Chair/Moderator and\r\nDiscussant Guidelines\" as well as copies of the abstracts or papers to be\r\ndiscussed will be emailed or mailed to you as soon as the sessions are\r\norganized.] CONFERENCE FEES (DUE MARCH 15, 2007) 1. Registration Fee ...................................$370 x __ = ______ 2. Participating Co-Author(s) & Panel Organizer only ................................$180 x __ = ______ 3. After March 15, 2007 Add Late Fee......$40 x __ =______ 4. Guest Fee (companions) ........................$65 x __ = ______ Total Amount Due .........................................…..... = ______ Note: Registration fees include \"guest speaker-awards\" luncheon, one\r\ncopy of the 2007 GLOBAL BUSINESS & ECONOMICS ANTHOLOGY, the quarterly\r\nGLOBAL BUSINESS & ECONOMICS REVIEW, and access to all Conference\r\npresentations and sessions. Current B&ESI members may deduct $120 from the\r\n$370 'Registration Fee' or, if applicable, the $180 'Participating Co-Author(s)\r\n& Panel Organizer Fee'. Payments: ______ My check is attached payable to\r\nB&ESI (in U.S. dollars drawn on a U.S. bank). Please charge my______ Visa ______ MasterCard or ______ American Express. Credit Card Number ______________________________ Exp. Date___________ Authorized Signature_________________________________________________ Refunds: Individuals applying for program participation but not accepted are\r\neligible for fee refunds. Cancellations must be in writing and are subject to a\r\n$40 handling fee. No refunds will be given for cancellations after May 15,\r\n2007. Refunds will be processed after the conference. PLEASE\r\nMAIL YOUR ABSTRACT(S)/PAPER(S) AND REGISTRATION FEES NO LATER THAN MARCH 15,\r\n2007 TO: B&ESI / Helen Kantarelis 64 Holden Street Worcester, MA 01605-3109 USA You may also reach us by Phone or E-mail: TELEPHONE: (508) 595-0089 EMAIL: hkan@besiweb.com B&ESI Web Site: http://www.besiweb.com SUBJECT CATEGORY TITLE AND NUMBER: ACCOUNTING (A1) MANAGEMENT SCIENCE (MS2) MARKETING (MR3) FINANCE & INTERNATIONAL FINANCE (F4) BUSINESS ETHICS (BE5) QUANTITATIVE METHODS (QM6) BUSINESS STATISTICS / ECONOMETRICS (BSE7) BUSINESS LAW / LAW & ECONOMICS (L8) ENTREPRENEURSHIP (E9) BUSINESS & ECONOMICS EDUCATION (BEE10) MICROECONOMICS (MIC11) GOVERNMENT REGULATION (GR12) INDUSTRIAL ORGANIZATION (IO13) GAME THEORY (G14) INTERNATIONAL BUSINESS / ECONOMICS (IBE15) LABOR ECONOMICS/HUMAN RESOURCES (LH16) ECONOMIC GROWTH & DEVELOPMENT (EGD17) BEHAVIORAL, HEALTH & EXPERIMENTAL ECONOMICS\r\n(BHE18) ENVIRONMENTAL BUSINESS / ECONOMICS (E19) MACROECONOMICS (MAC20) MONETARY ECONOMICS (ME21) GOVERNMENT FINANCE\r\n(GF22) URBAN,\r\nRURAL & REGIONAL ECONOMICS (URR23) OTHER - PLEASE\r\nSPECIFY (O24) if !supportEmptyParas endif HOTEL\r\nAMBASSADEUR - RESERVATION FORM [2007 Business & Economics\r\nSociety International (B&ESI) Conference, July 16-20] if !supportEmptyParas endif Hotel Ambassadeur, where the event will take place, makes available\r\nvarious rates with or without breakfast. Subject to hotel availability, for the\r\nbest room rates, please book on your own via internet brokers as early as\r\npossible. if !supportEmptyParas endif Ablock of rooms at 159 Euros for\r\nsingle (189 Euros for double), with breakfast, has been reserved until June 15,\r\n2007 ; reservations made after that date will be subject to hotel\r\navailability and rates. For these rates, please reference your reservation as\r\nfollows: “ 2007 Business & Economics\r\nSociety International (B&ESI) Conference, July 17-20”; you may book\r\ndirectly to the hotel via post, email attachment or fax. You may pay by\r\ninternational money order (payable in Euros to Hotel Ambassadeur or credit card\r\n(Visa, Diners Club, MasterCard, American Express.) The first night's deposit is\r\nrequired with reservation. if !supportEmptyParas endif Last Name:\r\n___________________________ First Name: __________________________ Middle\r\nInitial: ____ if !supportEmptyParas endif Address:\r\n_______________________________________________________________________________ if !supportEmptyParas endif Telephone: ____________________________________\r\nFax: ____________________________________ if !supportEmptyParas endif E-mail:\r\n____________________________________________________ if !supportEmptyParas endif ___ My international\r\nmoney order is attached payable in Euros to “Hotel Ambassadeur\". if !supportEmptyParas endif Please charge my: Visa ___ Diners\r\nClub___ MasterCard___ or, American Express____ if !supportEmptyParas endif Arrival date:______________\r\nDeparture date:________________ Smoking:___ Non-Smoking:___ if !supportEmptyParas endif Single:___ Double:___ King\r\nBed:___ Two-Bedded Room:___ Number of People in Room:___ if !supportEmptyParas endif Credit Card Number ______________________________\r\nExp. Date ___________ if !supportEmptyParas endif Authorized\r\nSignature__________________________________________________ if !supportEmptyParas endif Please keep a copy of this\r\nform for your records and mail or fax the original to: if !supportEmptyParas endif HOTEL AMBASSADEUR 50-52, Chemin des Sables – BP 49 06161\r\nJuan-les-Pins Cedex Antibes, France Telephone: + 33 (0)4 92 93 30 99, Fax: + 33 (0)4 93 67 79 85 Email: manager@hotel-ambassadeur.com ,\r\nHotel Web Site: http://www.hotel-ambassadeur.com/ PLEASE DISTRIBUTE\r\nTHIS ANNOUNCEMENT TO YOUR COLLEAGUES AND FRIENDS. THANK YOU!"
    }
  ]
}